nipoppy/__init__.py
nipoppy/_version.py
nipoppy/base.py
nipoppy/console.py
nipoppy/container.py
nipoppy/env.py
nipoppy/layout.py
nipoppy/logger.py
nipoppy/pipeline_validation.py
nipoppy/zenodo_api.py
nipoppy/cli/__init__.py
nipoppy/cli/cli.py
nipoppy/cli/options.py
nipoppy/cli/pipeline_catalog.py
nipoppy/config/__init__.py
nipoppy/config/boutiques.py
nipoppy/config/container.py
nipoppy/config/hpc.py
nipoppy/config/main.py
nipoppy/config/pipeline.py
nipoppy/config/pipeline_step.py
nipoppy/config/tracker.py
nipoppy/data/examples/sample_dicom_dir_map.tsv
nipoppy/data/examples/sample_global_config.json
nipoppy/data/examples/sample_manifest.tsv
nipoppy/data/hpc/clusters.yaml
nipoppy/data/hpc/job_script_template.sh
nipoppy/data/hpc/sge.yaml
nipoppy/data/hpc/slurm.yaml
nipoppy/data/layouts/layout-0.1.0.json
nipoppy/data/layouts/layout-0.2.x.json
nipoppy/data/layouts/layout-0.3.x.json
nipoppy/data/layouts/layout-default.json
nipoppy/data/template_pipeline/config-bidsification.json
nipoppy/data/template_pipeline/config-extraction.json
nipoppy/data/template_pipeline/config-processing.json
nipoppy/data/template_pipeline/descriptor.json
nipoppy/data/template_pipeline/hpc.json
nipoppy/data/template_pipeline/invocation.json
nipoppy/data/template_pipeline/pybids_ignore.json
nipoppy/data/template_pipeline/tracker.json
nipoppy/data/template_pipeline/zenodo.json
nipoppy/tabular/__init__.py
nipoppy/tabular/base.py
nipoppy/tabular/curation_status.py
nipoppy/tabular/dicom_dir_map.py
nipoppy/tabular/manifest.py
nipoppy/tabular/processing_status.py
nipoppy/utils/__init__.py
nipoppy/utils/bids.py
nipoppy/utils/html.py
nipoppy/utils/utils.py
nipoppy/workflows/__init__.py
nipoppy/workflows/base.py
nipoppy/workflows/bids_conversion.py
nipoppy/workflows/dataset_init.py
nipoppy/workflows/dataset_status.py
nipoppy/workflows/dicom_reorg.py
nipoppy/workflows/extractor.py
nipoppy/workflows/pipeline.py
nipoppy/workflows/processing_runner.py
nipoppy/workflows/runner.py
nipoppy-0.4.2.dist-info/METADATA
nipoppy-0.4.2.dist-info/WHEEL
nipoppy-0.4.2.dist-info/entry_points.txt
nipoppy-0.4.2.dist-info/licenses/LICENSE
nipoppy-0.4.2.dist-info/RECORD
