Metadata-Version: 2.4
Name: nipoppy
Version: 0.4.2
Summary: Standardized organization and processing of neuroimaging-clinical datasets
Author: Nipoppy developpers
License: MIT License
License-File: LICENSE
Classifier: Intended Audience :: Developers
Classifier: Intended Audience :: Science/Research
Classifier: License :: OSI Approved
Classifier: Operating System :: POSIX
Classifier: Operating System :: Unix
Classifier: Programming Language :: Python
Classifier: Topic :: Scientific/Engineering
Classifier: Topic :: Software Development
Requires-Python: >=3.9
Requires-Dist: boutiques>=0.5.31
Requires-Dist: click
Requires-Dist: httpx
Requires-Dist: jinja2
Requires-Dist: pandas
Requires-Dist: pybids!=0.18.0
Requires-Dist: pydantic
Requires-Dist: pydicom!=3.0.0
Requires-Dist: pysqa[sge]>=0.2.4
Requires-Dist: requests
Requires-Dist: rich
Requires-Dist: rich-click
Requires-Dist: typing-extensions
Provides-Extra: dev
Requires-Dist: fids>=0.1.0; extra == 'dev'
Requires-Dist: furo; extra == 'dev'
Requires-Dist: joblib; extra == 'dev'
Requires-Dist: mdit-py-plugins; extra == 'dev'
Requires-Dist: myst-parser; extra == 'dev'
Requires-Dist: packaging; extra == 'dev'
Requires-Dist: pre-commit; extra == 'dev'
Requires-Dist: pytest-cov; extra == 'dev'
Requires-Dist: pytest-httpx; extra == 'dev'
Requires-Dist: pytest-mock; extra == 'dev'
Requires-Dist: pytest-xdist; extra == 'dev'
Requires-Dist: pytest>=6.0.0; extra == 'dev'
Requires-Dist: sphinx; extra == 'dev'
Requires-Dist: sphinx-autoapi; extra == 'dev'
Requires-Dist: sphinx-click; extra == 'dev'
Requires-Dist: sphinx-copybutton; extra == 'dev'
Requires-Dist: sphinx-design; extra == 'dev'
Requires-Dist: sphinx-github-changelog; extra == 'dev'
Requires-Dist: sphinx-hoverxref; extra == 'dev'
Requires-Dist: sphinx-jsonschema; extra == 'dev'
Requires-Dist: sphinx-togglebutton; extra == 'dev'
Requires-Dist: trogon; extra == 'dev'
Provides-Extra: doc
Requires-Dist: furo; extra == 'doc'
Requires-Dist: mdit-py-plugins; extra == 'doc'
Requires-Dist: myst-parser; extra == 'doc'
Requires-Dist: sphinx; extra == 'doc'
Requires-Dist: sphinx-autoapi; extra == 'doc'
Requires-Dist: sphinx-click; extra == 'doc'
Requires-Dist: sphinx-copybutton; extra == 'doc'
Requires-Dist: sphinx-design; extra == 'doc'
Requires-Dist: sphinx-github-changelog; extra == 'doc'
Requires-Dist: sphinx-hoverxref; extra == 'doc'
Requires-Dist: sphinx-jsonschema; extra == 'doc'
Requires-Dist: sphinx-togglebutton; extra == 'doc'
Provides-Extra: gui
Requires-Dist: trogon; extra == 'gui'
Provides-Extra: parallel
Requires-Dist: joblib; extra == 'parallel'
Provides-Extra: test
Requires-Dist: fids>=0.1.0; extra == 'test'
Requires-Dist: joblib; extra == 'test'
Requires-Dist: packaging; extra == 'test'
Requires-Dist: pytest-cov; extra == 'test'
Requires-Dist: pytest-httpx; extra == 'test'
Requires-Dist: pytest-mock; extra == 'test'
Requires-Dist: pytest-xdist; extra == 'test'
Requires-Dist: pytest>=6.0.0; extra == 'test'
Requires-Dist: trogon; extra == 'test'
Provides-Extra: tests
Requires-Dist: fids>=0.1.0; extra == 'tests'
Requires-Dist: joblib; extra == 'tests'
Requires-Dist: packaging; extra == 'tests'
Requires-Dist: pytest-cov; extra == 'tests'
Requires-Dist: pytest-httpx; extra == 'tests'
Requires-Dist: pytest-mock; extra == 'tests'
Requires-Dist: pytest-xdist; extra == 'tests'
Requires-Dist: pytest>=6.0.0; extra == 'tests'
Requires-Dist: trogon; extra == 'tests'
Provides-Extra: tui
Requires-Dist: trogon; extra == 'tui'
